Metadata-Version: 1.1
Name: django-excel-data-sync
Version: 0.3.0
Summary: Creates XLS sheets to upload data into django models
Home-page: https://github.com/saxix/dj-excel-data-sync
Author: Stefano Apostolico
Author-email: s.apostolico@gmail.com
License: MIT
Keywords: django excel
Platform: UNKNOWN
Classifier: Development Status :: 3 - Alpha
Classifier: Framework :: Django
Classifier: Framework :: Django :: 1.8
Classifier: Framework :: Django :: 1.9
Classifier: Framework :: Django :: 1.10
Classifier: Intended Audience :: Developers
Classifier: License :: OSI Approved :: BSD License
Classifier: Natural Language :: English
Classifier: Programming Language :: Python :: 2
Classifier: Programming Language :: Python :: 2.7
Classifier: Programming Language :: Python :: 3
Classifier: Programming Language :: Python :: 3.2
Classifier: Programming Language :: Python :: 3.3
Classifier: Programming Language :: Python :: 3.4
Classifier: Programming Language :: Python :: 3.5
